nanga/__init__.py
nanga/pipelines/__init__.py
nanga/pipelines/base.py
nanga/pipelines/sarcat.py
nanga/pipelines/summarization.py
nanga/sarcat/__init__.py
nanga/sarcat/inference.py
nanga/sarcat/losses.py
nanga/sarcat/options.py
nanga/sarcat/train.py
nanga/sarcat/models/__init__.py
nanga/sarcat/models/bert_models.py
nanga/sarcat/models/modules.py
nanga/sarcat/models/rnn_models.py
nanga/sarcat/models/legacy/__init__.py
nanga/sarcat/models/legacy/db.py
nanga/sarcat/models/legacy/inference.py
nanga/sarcat/models/legacy/modules.py
nanga/sarcat/models/legacy/utils.py
nanga/sarcat/predictions/__init__.py
nanga/sarcat/predictions/classification.py
nanga/sarcat/predictions/utils.py
nanga/summarization/__init__.py
nanga/summarization/inference.py
nanga/summarization/utils.py
nanga/summarization/core/__init__.py
nanga/summarization/core/processor.py
nanga/summarization/core/clusters/__init__.py
nanga/summarization/core/clusters/cluster_feature.py
nanga/summarization/core/extractive/__init__.py
nanga/summarization/core/extractive/extractive_summarizer.py
nanga/summarization/core/texts/__init__.py
nanga/summarization/core/texts/sentence_handler.py
nanga/summarization/models/__init__.py
nanga/summarization/models/bert_models.py
nanga/utils/__init__.py
nanga/utils/log.py
nanga-1.0.2.dist-info/METADATA
nanga-1.0.2.dist-info/WHEEL
nanga-1.0.2.dist-info/top_level.txt
nanga-1.0.2.dist-info/RECORD
