Metadata-Version: 2.1
Name: nanga
Version: 1.0.2
Summary: NLP tasks
Home-page: UNKNOWN
Author: Fréjus A.A. Laleye
Author-email: frejus.laleye@gmail.com
Maintainer: Fréjus A. A. Laleye
Maintainer-email: frejus.laleye@gmail.com
License: UNKNOWN
Keywords: Natural language processing,Summarization,Text classification
Platform: UNKNOWN
Classifier: Development Status :: 3 - Alpha
Classifier: Intended Audience :: Developers
Classifier: Programming Language :: Python :: 3
Classifier: Operating System :: OS Independent
Requires-Python: >=3.7
Requires-Dist: transformers (>=4.20.1)
Requires-Dist: joblib (==1.1.0)
Requires-Dist: torch (>=2.0.1)
Requires-Dist: spacy (==3.4.4)
Requires-Dist: scikit-learn (==1.1.1)
Requires-Dist: torchtext (>=0.15.2)
